swodl_interpreter/__main__.py
swodl_interpreter/ast.py
swodl_interpreter/bpm.py
swodl_interpreter/convertor.py
swodl_interpreter/doc.py
swodl_interpreter/fake.py
swodl_interpreter/inbuild_functions.py
swodl_interpreter/interpreter.py
swodl_interpreter/lexer.py
swodl_interpreter/lint.py
swodl_interpreter/mock.py
swodl_interpreter/parser.py
swodl_interpreter/repl.py
swodl_interpreter/runner.py
swodl_interpreter/storage.py
swodl_interpreter/token.py
swodl_interpreter/web_service_resolver.py
swodl_interpreter/asts/__init__.py
swodl_interpreter/asts/_list.py
swodl_interpreter/asts/_return.py
swodl_interpreter/asts/assign.py
swodl_interpreter/asts/bin_op.py
swodl_interpreter/asts/comment.py
swodl_interpreter/asts/compound.py
swodl_interpreter/asts/condition.py
swodl_interpreter/asts/cycle.py
swodl_interpreter/asts/declare_web.py
swodl_interpreter/asts/delay.py
swodl_interpreter/asts/do_cycle.py
swodl_interpreter/asts/error.py
swodl_interpreter/asts/execution_exception.py
swodl_interpreter/asts/exit.py
swodl_interpreter/asts/func_decl.py
swodl_interpreter/asts/goto_sub.py
swodl_interpreter/asts/include.py
swodl_interpreter/asts/label.py
swodl_interpreter/asts/procedure_call.py
swodl_interpreter/asts/retry.py
swodl_interpreter/asts/status.py
swodl_interpreter/asts/string.py
swodl_interpreter/asts/struct.py
swodl_interpreter/asts/try_catch.py
swodl_interpreter/asts/unary_op.py
swodl_interpreter/lexers/__init__.py
swodl_interpreter/lexers/bool.py
swodl_interpreter/lexers/comments.py
swodl_interpreter/lexers/id.py
swodl_interpreter/lexers/keyword.py
swodl_interpreter/lexers/label.py
swodl_interpreter/lexers/method_call.py
swodl_interpreter/lexers/number.py
swodl_interpreter/lexers/operation.py
swodl_interpreter/lexers/status.py
swodl_interpreter/lexers/string.py
swodl_interpreter/lexers/symbol.py
swodl_interpreter/lexers/whitespace.py
swodl_interpreter-1.0.1.dist-info/LICENSE
swodl_interpreter-1.0.1.dist-info/METADATA
swodl_interpreter-1.0.1.dist-info/WHEEL
swodl_interpreter-1.0.1.dist-info/entry_points.txt
swodl_interpreter-1.0.1.dist-info/top_level.txt
swodl_interpreter-1.0.1.dist-info/RECORD
