Metadata-Version: 2.1
Name: swodl-interpreter
Version: 1.0.1
Summary: SWoDL interpreter.
Home-page: https://gitlab.com/vladku/swodl_interpreter
Author: Vladyslav Kurovskyi
License: MIT
Classifier: Programming Language :: Python :: 3
Classifier: License :: OSI Approved :: MIT License
Classifier: Operating System :: OS Independent
License-File: LICENSE
Requires-Dist: click
Requires-Dist: inflection
Requires-Dist: lxml
Requires-Dist: pre-commit
Requires-Dist: xmltodict
Requires-Dist: zeep
